rpcpdb-0.4.4.dist-info/DESCRIPTION.rst
rpcpdb-0.4.4.dist-info/top_level.txt
rpcpdb-0.4.4.dist-info/METADATA
rpcpdb-0.4.4.dist-info/RECORD
rpcpdb-0.4.4.dist-info/WHEEL
rpcpdb-0.4.4.dist-info/pydist.json
rpcpdb/__init__.py
rpcpdb/pyro_debug.py
rpcpdb/func_trace.py
rpcpdb/cli_xmlrpc.py
rpcpdb/xmlrpc_server.py
rpcpdb/updb.py
rpcpdb/termsock.py
rpcpdb/test_server.py
rpcpdb/cli.py
rpcpdb/cli_pyro.py
rpcpdb/pyro_client.py
rpcpdb/xmlrpc_debug.py
rpcpdb/pyro_server.py
rpcpdb/inspect_helper.py
rpcpdb/xmlrpc_client.py
